scoobydoo/__init__.py
scoobydoo/catchphrases.py
scoobydoo/characters.py
scoobydoo/main.py
scoobydoo-0.1.dist-info/METADATA
scoobydoo-0.1.dist-info/WHEEL
scoobydoo-0.1.dist-info/entry_points.txt
scoobydoo-0.1.dist-info/top_level.txt
scoobydoo-0.1.dist-info/RECORD
